{
  "updated_at_utc": "2026-02-17T07:51:39.036931+00:00",
  "vs_currency": "usd",
  "prices": {
    "aave": {
      "usd": 125.09,
      "usd_24h_change": -1.070729897255466,
      "usd_7d_change": 14.791732199153593,
      "usd_30d_change": -27.749721264915085,
      "usd_1y_change": -51.77640763000665
    },
    "binancecoin": {
      "usd": 622.67,
      "usd_24h_change": 1.6044208351738962,
      "usd_7d_change": -0.9055092265709639,
      "usd_30d_change": -34.21604702860646,
      "usd_1y_change": -7.738158816327859
    },
    "bitcoin": {
      "usd": 68412,
      "usd_24h_change": -0.157880388830706,
      "usd_7d_change": -0.6324247554634578,
      "usd_30d_change": -28.081836315720764,
      "usd_1y_change": -29.00675895035198
    },
    "bitcoin-cash": {
      "usd": 561.01,
      "usd_24h_change": 0.7273117669142094,
      "usd_7d_change": 7.438000669818614,
      "usd_30d_change": -5.621740771100734,
      "usd_1y_change": 70.92060188505434
    },
    "cardano": {
      "usd": 0.28925,
      "usd_24h_change": 3.358468034032716,
      "usd_7d_change": 8.930020170831392,
      "usd_30d_change": -26.77169391340428,
      "usd_1y_change": -63.87848644388233
    },
    "dogecoin": {
      "usd": 0.099876,
      "usd_24h_change": -1.9766767573088884,
      "usd_7d_change": 7.018238104385412,
      "usd_30d_change": -27.2010580367169,
      "usd_1y_change": -61.98511823206522
    },
    "ethereum": {
      "usd": 1984.99,
      "usd_24h_change": 0.7727393945786308,
      "usd_7d_change": -3.2561493560954764,
      "usd_30d_change": -40.11179299513989,
      "usd_1y_change": -25.600065132650684
    },
    "litecoin": {
      "usd": 55.53,
      "usd_24h_change": 2.6122667913896396,
      "usd_7d_change": 3.46026747061711,
      "usd_30d_change": -25.784196803905008,
      "usd_1y_change": -55.744960290086865
    },
    "monero": {
      "usd": 335.05,
      "usd_24h_change": 5.894544148229271,
      "usd_7d_change": 0.41704113621877986,
      "usd_30d_change": -43.022825430104106,
      "usd_1y_change": 44.288376686488725
    },
    "ripple": {
      "usd": 1.47,
      "usd_24h_change": 0.8522590478675177,
      "usd_7d_change": 3.8067872679676866,
      "usd_30d_change": -28.431871494234418,
      "usd_1y_change": -45.21854617812247
    },
    "shiba-inu": {
      "usd": 6.55e-06,
      "usd_24h_change": -0.9562634626712974,
      "usd_7d_change": 8.677504388555036,
      "usd_30d_change": -21.94206804485112,
      "usd_1y_change": -58.77198722731081
    },
    "solana": {
      "usd": 86.39,
      "usd_24h_change": 1.414735411164745,
      "usd_7d_change": 0.6779487704660613,
      "usd_30d_change": -39.49783061462783,
      "usd_1y_change": -52.971857268232995
    },
    "stellar": {
      "usd": 0.167426,
      "usd_24h_change": -0.5031627287238705,
      "usd_7d_change": 7.103644768061656,
      "usd_30d_change": -26.6735942252394,
      "usd_1y_change": -50.93994490626168
    },
    "the-open-network": {
      "usd": 1.44,
      "usd_24h_change": 0.31425162854198174,
      "usd_7d_change": 6.626759794331527,
      "usd_30d_change": -16.113408716912474,
      "usd_1y_change": -62.0653543590165
    },
    "tron": {
      "usd": 0.284352,
      "usd_24h_change": 1.7171150866502312,
      "usd_7d_change": 2.5305198386834085,
      "usd_30d_change": -11.000586378901383,
      "usd_1y_change": 17.495632950373004
    },
    "zcash": {
      "usd": 286.96,
      "usd_24h_change": 1.4620839168962103,
      "usd_7d_change": 22.728552965292,
      "usd_30d_change": -27.528601336693292,
      "usd_1y_change": 718.1186700096706
    }
  }
}