{
  "updated_at_utc": "2025-12-24T07:07:00.300128+00:00",
  "vs_currency": "usd",
  "prices": {
    "aave": {
      "usd": 147.98,
      "usd_24h_change": -3.9391617429610157,
      "usd_7d_change": -20.042653791814562,
      "usd_30d_change": -14.24100455402948,
      "usd_1y_change": -60.84344406231011
    },
    "binancecoin": {
      "usd": 839.67,
      "usd_24h_change": -1.1502661694653769,
      "usd_7d_change": -2.998556324077012,
      "usd_30d_change": -1.615596514404632,
      "usd_1y_change": 21.11604561793601
    },
    "bitcoin": {
      "usd": 86963,
      "usd_24h_change": -0.5573493878903784,
      "usd_7d_change": 0.2426556618327202,
      "usd_30d_change": -0.4855122739842698,
      "usd_1y_change": -7.9141077367579
    },
    "bitcoin-cash": {
      "usd": 572.17,
      "usd_24h_change": -1.7322379187341803,
      "usd_7d_change": 4.725786779316447,
      "usd_30d_change": 4.4218859155049275,
      "usd_1y_change": 24.562805083197485
    },
    "cardano": {
      "usd": 0.356819,
      "usd_24h_change": -2.174436311246496,
      "usd_7d_change": -6.147801874916538,
      "usd_30d_change": -14.706070069670579,
      "usd_1y_change": -60.7273473272396
    },
    "dogecoin": {
      "usd": 0.127276,
      "usd_24h_change": -2.649012627289098,
      "usd_7d_change": -2.735162115257473,
      "usd_30d_change": -13.853928864022771,
      "usd_1y_change": -60.62016514091635
    },
    "ethereum": {
      "usd": 2933.69,
      "usd_24h_change": -0.9696436365054671,
      "usd_7d_change": -0.06614863880886526,
      "usd_30d_change": 2.412550415836722,
      "usd_1y_change": -14.052791722051856
    },
    "litecoin": {
      "usd": 75.89,
      "usd_24h_change": -1.1649731918567092,
      "usd_7d_change": -3.862283365920162,
      "usd_30d_change": -9.993060408306992,
      "usd_1y_change": -28.576248745488208
    },
    "monero": {
      "usd": 426.93,
      "usd_24h_change": -2.6177604792938887,
      "usd_7d_change": -0.0667155878576839,
      "usd_30d_change": 11.026873882317126,
      "usd_1y_change": 127.8544133033017
    },
    "ripple": {
      "usd": 1.85,
      "usd_24h_change": -1.7457655646737988,
      "usd_7d_change": -3.6468959967566548,
      "usd_30d_change": -11.383101853349222,
      "usd_1y_change": -17.647522649233974
    },
    "shiba-inu": {
      "usd": 7.02e-06,
      "usd_24h_change": -1.8750098127739576,
      "usd_7d_change": -10.118253918803411,
      "usd_30d_change": -12.886657302696177,
      "usd_1y_change": -68.77944011760636
    },
    "solana": {
      "usd": 121.53,
      "usd_24h_change": -2.296686163344192,
      "usd_7d_change": -4.8162018245218885,
      "usd_30d_change": -8.52453706130823,
      "usd_1y_change": -36.48829718630982
    },
    "stellar": {
      "usd": 0.214169,
      "usd_24h_change": -1.4010701230636995,
      "usd_7d_change": -1.8473490726900879,
      "usd_30d_change": -14.122893792885199,
      "usd_1y_change": -42.46297598904234
    },
    "the-open-network": {
      "usd": 1.46,
      "usd_24h_change": 0.6962306066839652,
      "usd_7d_change": -5.291399061613012,
      "usd_30d_change": -0.700451140762281,
      "usd_1y_change": -74.05879046242242
    },
    "tron": {
      "usd": 0.282076,
      "usd_24h_change": -0.4755322349616074,
      "usd_7d_change": 0.6998272194230039,
      "usd_30d_change": 1.7781032421809901,
      "usd_1y_change": 11.87912104636291
    },
    "zcash": {
      "usd": 407.36,
      "usd_24h_change": -2.334839105519743,
      "usd_7d_change": 4.2880100273649475,
      "usd_30d_change": -27.15202167486176,
      "usd_1y_change": 501.21234592646687
    }
  }
}