{
  "updated_at_utc": "2025-12-16T11:39:19.633132+00:00",
  "vs_currency": "usd",
  "prices": {
    "aave": {
      "usd": 187.89,
      "usd_24h_change": -3.7758255531186626,
      "usd_7d_change": -0.06308720602830681,
      "usd_30d_change": 3.835396847402086,
      "usd_1y_change": -51.902656124049884
    },
    "binancecoin": {
      "usd": 863.73,
      "usd_24h_change": -2.8837510105173565,
      "usd_7d_change": -2.6118415549537213,
      "usd_30d_change": -8.78340625734183,
      "usd_1y_change": 21.608671733335537
    },
    "bitcoin": {
      "usd": 87138,
      "usd_24h_change": -2.976056436675608,
      "usd_7d_change": -3.4428061058452517,
      "usd_30d_change": -9.59779837850613,
      "usd_1y_change": -16.84159350126766
    },
    "bitcoin-cash": {
      "usd": 542.73,
      "usd_24h_change": -4.256813950607709,
      "usd_7d_change": -5.122535749138224,
      "usd_30d_change": 8.066507711295255,
      "usd_1y_change": 1.4821225668021196
    },
    "cardano": {
      "usd": 0.387678,
      "usd_24h_change": -4.1446012833292,
      "usd_7d_change": -9.288415909849707,
      "usd_30d_change": -23.508429318368457,
      "usd_1y_change": -64.05541485389395
    },
    "dogecoin": {
      "usd": 0.131727,
      "usd_24h_change": -3.809290946968043,
      "usd_7d_change": -6.017313523873739,
      "usd_30d_change": -20.08084442846416,
      "usd_1y_change": -67.22887110706907
    },
    "ethereum": {
      "usd": 2954.58,
      "usd_24h_change": -6.480619242817472,
      "usd_7d_change": -4.8956691191148085,
      "usd_30d_change": -8.739456762201177,
      "usd_1y_change": -25.200706588744115
    },
    "litecoin": {
      "usd": 78.61,
      "usd_24h_change": -3.029763638741563,
      "usd_7d_change": -5.555171399223853,
      "usd_30d_change": -23.088574654797124,
      "usd_1y_change": -33.79757127480787
    },
    "monero": {
      "usd": 417.92,
      "usd_24h_change": 0.4575022122482602,
      "usd_7d_change": 11.932212894135352,
      "usd_30d_change": -1.2431844690904958,
      "usd_1y_change": 95.4990376262538
    },
    "ripple": {
      "usd": 1.92,
      "usd_24h_change": -3.3342398608064547,
      "usd_7d_change": -6.5581193754218505,
      "usd_30d_change": -15.310913166940873,
      "usd_1y_change": -19.478608125521653
    },
    "shiba-inu": {
      "usd": 7.97e-06,
      "usd_24h_change": -2.8519938060980263,
      "usd_7d_change": -6.416270038668018,
      "usd_30d_change": -13.391423839210015,
      "usd_1y_change": -70.52720513057255
    },
    "solana": {
      "usd": 128.35,
      "usd_24h_change": -3.3192308287108077,
      "usd_7d_change": -3.2127694314221196,
      "usd_30d_change": -10.140895329871023,
      "usd_1y_change": -41.08549042487773
    },
    "stellar": {
      "usd": 0.222901,
      "usd_24h_change": -3.8978851806279176,
      "usd_7d_change": -6.697888632461383,
      "usd_30d_change": -14.900678723830769,
      "usd_1y_change": -46.27852691852399
    },
    "the-open-network": {
      "usd": 1.53,
      "usd_24h_change": -2.9184606477470307,
      "usd_7d_change": -5.464873179970198,
      "usd_30d_change": -17.719559073262715,
      "usd_1y_change": -75.49661775955745
    },
    "tron": {
      "usd": 0.279709,
      "usd_24h_change": -0.7132209974336526,
      "usd_7d_change": -0.34898507219688474,
      "usd_30d_change": -6.381463630454015,
      "usd_1y_change": -0.5795910008432503
    },
    "zcash": {
      "usd": 395.37,
      "usd_24h_change": -3.4661197474844188,
      "usd_7d_change": -3.579295363419128,
      "usd_30d_change": -43.76258494150473,
      "usd_1y_change": 576.2637239987727
    }
  }
}