{
  "updated_at_utc": "2025-12-15T23:16:07.503585+00:00",
  "vs_currency": "usd",
  "prices": {
    "aave": {
      "usd": 188.77,
      "usd_24h_change": 0.22340360339835127,
      "usd_7d_change": -2.5600305914477075,
      "usd_30d_change": 6.085772765038468,
      "usd_1y_change": -47.561909342974865
    },
    "binancecoin": {
      "usd": 857.0,
      "usd_24h_change": -2.244305862962911,
      "usd_7d_change": -5.242131743022795,
      "usd_30d_change": -7.495620467134824,
      "usd_1y_change": 20.870387848120256
    },
    "bitcoin": {
      "usd": 86417,
      "usd_24h_change": -1.8464505105639628,
      "usd_7d_change": -5.403460236439024,
      "usd_30d_change": -9.150098304490111,
      "usd_1y_change": -15.963639234270202
    },
    "bitcoin-cash": {
      "usd": 534.98,
      "usd_24h_change": -3.9128349035748515,
      "usd_7d_change": -8.217288649439096,
      "usd_30d_change": 7.1577881835569945,
      "usd_1y_change": 1.3347335574366566
    },
    "cardano": {
      "usd": 0.387146,
      "usd_24h_change": -2.3272006350632606,
      "usd_7d_change": -11.304121690246463,
      "usd_30d_change": -22.478830157997358,
      "usd_1y_change": -63.57765349333119
    },
    "dogecoin": {
      "usd": 0.129461,
      "usd_24h_change": -3.3060457991260486,
      "usd_7d_change": -10.00066188878116,
      "usd_30d_change": -20.190176827224153,
      "usd_1y_change": -67.51506983161867
    },
    "ethereum": {
      "usd": 2967.08,
      "usd_24h_change": -3.2591136366794435,
      "usd_7d_change": -5.727915508695955,
      "usd_30d_change": -5.886344077583765,
      "usd_1y_change": -23.052085071780283
    },
    "litecoin": {
      "usd": 77.73,
      "usd_24h_change": -1.141352196246514,
      "usd_7d_change": -7.822951378787464,
      "usd_30d_change": -23.92818281834851,
      "usd_1y_change": -33.25299582211387
    },
    "monero": {
      "usd": 409.47,
      "usd_24h_change": 0.4604969018304078,
      "usd_7d_change": 8.543884357121936,
      "usd_30d_change": -1.5608960926095254,
      "usd_1y_change": 90.62136369024772
    },
    "ripple": {
      "usd": 1.9,
      "usd_24h_change": -4.586781133453846,
      "usd_7d_change": -9.144366225339496,
      "usd_30d_change": -14.728166961358136,
      "usd_1y_change": -20.20404118930616
    },
    "shiba-inu": {
      "usd": 7.9e-06,
      "usd_24h_change": -2.0153617818367433,
      "usd_7d_change": -7.821895264636369,
      "usd_30d_change": -12.385137051565332,
      "usd_1y_change": -70.83828809327832
    },
    "solana": {
      "usd": 126.91,
      "usd_24h_change": -2.288862390792667,
      "usd_7d_change": -5.573476951629623,
      "usd_30d_change": -8.593316653876922,
      "usd_1y_change": -41.493455158384926
    },
    "stellar": {
      "usd": 0.22079,
      "usd_24h_change": -3.524923556378859,
      "usd_7d_change": -9.299875274713386,
      "usd_30d_change": -15.059310918515761,
      "usd_1y_change": -47.31506203886172
    },
    "the-open-network": {
      "usd": 1.49,
      "usd_24h_change": -4.0254342413163355,
      "usd_7d_change": -9.3357282296092,
      "usd_30d_change": -20.130422077626793,
      "usd_1y_change": -76.48666014237938
    },
    "tron": {
      "usd": 0.278769,
      "usd_24h_change": 0.689029999137491,
      "usd_7d_change": -1.5611132071070537,
      "usd_30d_change": -4.952465383596245,
      "usd_1y_change": -0.47519188673711654
    },
    "zcash": {
      "usd": 411.67,
      "usd_24h_change": 3.168814026271452,
      "usd_7d_change": -1.0416514423664889,
      "usd_30d_change": -39.512402180003285,
      "usd_1y_change": 620.1852702715406
    }
  }
}