{
  "updated_at_utc": "2026-01-13T09:30:23.651803+00:00",
  "vs_currency": "usd",
  "prices": {
    "aave": {
      "usd": 170.63,
      "usd_24h_change": 3.501735416596034,
      "usd_7d_change": -0.88336407630913,
      "usd_30d_change": -12.443293459486595,
      "usd_1y_change": -37.49522205744441
    },
    "binancecoin": {
      "usd": 909.02,
      "usd_24h_change": 0.9019266441168357,
      "usd_7d_change": 0.2186574527222822,
      "usd_30d_change": 1.3244285453329947,
      "usd_1y_change": 33.3829835945821
    },
    "bitcoin": {
      "usd": 92436,
      "usd_24h_change": 1.8630721172862508,
      "usd_7d_change": -0.8249694057117732,
      "usd_30d_change": 2.439392672191096,
      "usd_1y_change": -1.1308884921305982
    },
    "bitcoin-cash": {
      "usd": 612.6,
      "usd_24h_change": -2.1280233308754677,
      "usd_7d_change": -4.284184481568606,
      "usd_30d_change": 6.082179858338672,
      "usd_1y_change": 42.7231293903599
    },
    "cardano": {
      "usd": 0.393861,
      "usd_24h_change": 1.7028210833262523,
      "usd_7d_change": -5.050634758773859,
      "usd_30d_change": -3.3412000563949897,
      "usd_1y_change": -57.875723886439914
    },
    "dogecoin": {
      "usd": 0.139681,
      "usd_24h_change": 2.1613674274606605,
      "usd_7d_change": -6.695360078511797,
      "usd_30d_change": 1.2431198383308413,
      "usd_1y_change": -57.400124566015386
    },
    "ethereum": {
      "usd": 3139.45,
      "usd_24h_change": 0.7619175915209546,
      "usd_7d_change": -2.4672549421756047,
      "usd_30d_change": 0.7254833974897651,
      "usd_1y_change": -1.8047212938015862
    },
    "litecoin": {
      "usd": 76.25,
      "usd_24h_change": -2.4047920827874156,
      "usd_7d_change": -8.213745549245736,
      "usd_30d_change": -5.836215367014089,
      "usd_1y_change": -22.7028928656778
    },
    "monero": {
      "usd": 682.77,
      "usd_24h_change": 17.573573067216472,
      "usd_7d_change": 52.84211399276596,
      "usd_30d_change": 65.0826467819784,
      "usd_1y_change": 245.36119360478108
    },
    "ripple": {
      "usd": 2.07,
      "usd_24h_change": 0.956676129491604,
      "usd_7d_change": -11.29873935712422,
      "usd_30d_change": 2.623863517003638,
      "usd_1y_change": -15.817881683311786
    },
    "shiba-inu": {
      "usd": 8.61e-06,
      "usd_24h_change": 2.0106273266301686,
      "usd_7d_change": -6.142289220523637,
      "usd_30d_change": 4.060395921533774,
      "usd_1y_change": -58.758221840343396
    },
    "solana": {
      "usd": 142.27,
      "usd_24h_change": 1.7552529760995041,
      "usd_7d_change": 3.380004137480573,
      "usd_30d_change": 7.043175715439204,
      "usd_1y_change": -21.878115647692983
    },
    "stellar": {
      "usd": 0.223888,
      "usd_24h_change": 1.8456031290476616,
      "usd_7d_change": -8.88196200186597,
      "usd_30d_change": -5.170168120814782,
      "usd_1y_change": -45.567768588503036
    },
    "the-open-network": {
      "usd": 1.76,
      "usd_24h_change": 0.6955819698889999,
      "usd_7d_change": -7.899639562248882,
      "usd_30d_change": 9.689830174158164,
      "usd_1y_change": -65.7665592558089
    },
    "tron": {
      "usd": 0.298966,
      "usd_24h_change": 0.3322501477162785,
      "usd_7d_change": 2.279310802666993,
      "usd_30d_change": 8.853754316269054,
      "usd_1y_change": 31.82137952342945
    },
    "zcash": {
      "usd": 405.08,
      "usd_24h_change": 1.7200423139390253,
      "usd_7d_change": -19.602818408930215,
      "usd_30d_change": -4.119977592564701,
      "usd_1y_change": 769.6984868999817
    }
  }
}