{
  "updated_at_utc": "2026-02-11T06:44:09.148734+00:00",
  "vs_currency": "usd",
  "prices": {
    "aave": {
      "usd": 106.47,
      "usd_24h_change": -3.2064670630035805,
      "usd_7d_change": -16.21177217197821,
      "usd_30d_change": -37.28207758111348,
      "usd_1y_change": -59.06543000520904
    },
    "binancecoin": {
      "usd": 602.29,
      "usd_24h_change": -4.883739823938535,
      "usd_7d_change": -20.195004745914265,
      "usd_30d_change": -33.55473453358332,
      "usd_1y_change": -5.849780378205623
    },
    "bitcoin": {
      "usd": 66945,
      "usd_24h_change": -3.0095985526882822,
      "usd_7d_change": -12.108394942762555,
      "usd_30d_change": -27.234014336619733,
      "usd_1y_change": -31.719783888354403
    },
    "bitcoin-cash": {
      "usd": 518.27,
      "usd_24h_change": -0.8208547271424621,
      "usd_7d_change": -2.092485671745754,
      "usd_30d_change": -19.215148315273257,
      "usd_1y_change": 52.63788990649076
    },
    "cardano": {
      "usd": 0.256731,
      "usd_24h_change": -2.9046254286407227,
      "usd_7d_change": -13.56480246650023,
      "usd_30d_change": -35.48830605330911,
      "usd_1y_change": -67.06051073838711
    },
    "dogecoin": {
      "usd": 0.090975,
      "usd_24h_change": -3.350745150395028,
      "usd_7d_change": -15.431679544657129,
      "usd_30d_change": -35.36746372268978,
      "usd_1y_change": -65.16322692802294
    },
    "ethereum": {
      "usd": 1955.45,
      "usd_24h_change": -3.6783761505602857,
      "usd_7d_change": -13.552155062493526,
      "usd_30d_change": -38.02499076518263,
      "usd_1y_change": -27.368265327526643
    },
    "litecoin": {
      "usd": 52.28,
      "usd_24h_change": -2.2171625546982767,
      "usd_7d_change": -13.060323391508508,
      "usd_30d_change": -34.62710306532725,
      "usd_1y_change": -60.17740732435423
    },
    "monero": {
      "usd": 344.22,
      "usd_24h_change": 4.110881690638491,
      "usd_7d_change": -10.754909607098414,
      "usd_30d_change": -39.90018636147468,
      "usd_1y_change": 56.58830468474982
    },
    "ripple": {
      "usd": 1.37,
      "usd_24h_change": -4.412942220474714,
      "usd_7d_change": -13.563923002674722,
      "usd_30d_change": -34.187707336941415,
      "usd_1y_change": -44.58064600806699
    },
    "shiba-inu": {
      "usd": 5.88e-06,
      "usd_24h_change": -2.131866601790632,
      "usd_7d_change": -12.746997936636179,
      "usd_30d_change": -31.833047255888996,
      "usd_1y_change": -63.51984187225925
    },
    "solana": {
      "usd": 81.32,
      "usd_24h_change": -4.645878092787438,
      "usd_7d_change": -16.25581299034101,
      "usd_30d_change": -42.956941872050734,
      "usd_1y_change": -60.069953230700676
    },
    "stellar": {
      "usd": 0.154755,
      "usd_24h_change": -1.7490259915963244,
      "usd_7d_change": -11.806370530857494,
      "usd_30d_change": -31.62644175274027,
      "usd_1y_change": -52.09683226648168
    },
    "the-open-network": {
      "usd": 1.31,
      "usd_24h_change": -2.640507850794332,
      "usd_7d_change": -5.611085548316464,
      "usd_30d_change": -25.13851593188753,
      "usd_1y_change": -65.62793739603913
    },
    "tron": {
      "usd": 0.274468,
      "usd_24h_change": -1.16640670967496,
      "usd_7d_change": -4.150387833038216,
      "usd_30d_change": -8.037674731615889,
      "usd_1y_change": 11.635779749788906
    },
    "zcash": {
      "usd": 238.25,
      "usd_24h_change": 1.1994774194474958,
      "usd_7d_change": -14.06488314969366,
      "usd_30d_change": -42.421321089644984,
      "usd_1y_change": 609.5691975921363
    }
  }
}