{
  "updated_at_utc": "2025-12-02T22:02:49.305096+00:00",
  "vs_currency": "usd",
  "prices": {
    "aave": {
      "usd": 187.7,
      "usd_24h_change": 11.352524365630803
    },
    "binancecoin": {
      "usd": 879.93,
      "usd_24h_change": 6.815190851013868
    },
    "bitcoin": {
      "usd": 91662,
      "usd_24h_change": 5.967644966189818
    },
    "bitcoin-cash": {
      "usd": 551.4,
      "usd_24h_change": 5.863379716774817
    },
    "cardano": {
      "usd": 0.437144,
      "usd_24h_change": 13.832346836087611
    },
    "dogecoin": {
      "usd": 0.146159,
      "usd_24h_change": 8.19269980142894
    },
    "ethereum": {
      "usd": 3000.51,
      "usd_24h_change": 7.468273480757806
    },
    "litecoin": {
      "usd": 83.11,
      "usd_24h_change": 7.534130753044238
    },
    "monero": {
      "usd": 413.67,
      "usd_24h_change": 3.024870219277323
    },
    "ripple": {
      "usd": 2.17,
      "usd_24h_change": 6.98025054641635
    },
    "shiba-inu": {
      "usd": 8.49e-06,
      "usd_24h_change": 5.818253495394055
    },
    "solana": {
      "usd": 139.19,
      "usd_24h_change": 10.510079195424023
    },
    "stellar": {
      "usd": 0.256404,
      "usd_24h_change": 9.654389175105523
    },
    "the-open-network": {
      "usd": 1.58,
      "usd_24h_change": 5.139064610819865
    },
    "tron": {
      "usd": 0.281604,
      "usd_24h_change": 1.2861876406177357
    },
    "zcash": {
      "usd": 310.0,
      "usd_24h_change": -9.534897746628024
    }
  }
}