{
  "updated_at_utc": "2026-01-18T11:49:14.316165+00:00",
  "vs_currency": "usd",
  "prices": {
    "aave": {
      "usd": 173.06,
      "usd_24h_change": -0.8866318506963665,
      "usd_7d_change": 4.023068723940653,
      "usd_30d_change": -4.396650262602809,
      "usd_1y_change": -44.51490381706077
    },
    "binancecoin": {
      "usd": 946.52,
      "usd_24h_change": 0.3782498664914786,
      "usd_7d_change": 3.8190537576659525,
      "usd_30d_change": 12.010366151456624,
      "usd_1y_change": 35.40770285953239
    },
    "bitcoin": {
      "usd": 95109,
      "usd_24h_change": -0.15733235919396937,
      "usd_7d_change": 4.955980862789482,
      "usd_30d_change": 8.014030057795086,
      "usd_1y_change": -7.807846384668254
    },
    "bitcoin-cash": {
      "usd": 591.71,
      "usd_24h_change": -0.4970776155822919,
      "usd_7d_change": -10.014409175919479,
      "usd_30d_change": -0.08626584777623461,
      "usd_1y_change": 27.513356570595754
    },
    "cardano": {
      "usd": 0.393352,
      "usd_24h_change": -0.388776544232061,
      "usd_7d_change": 0.6279590965431222,
      "usd_30d_change": 7.5708863386307,
      "usd_1y_change": -63.13622236380352
    },
    "dogecoin": {
      "usd": 0.137249,
      "usd_24h_change": -0.28853230359049864,
      "usd_7d_change": -1.7879480574700957,
      "usd_30d_change": 7.117959859327527,
      "usd_1y_change": -65.33048853275983
    },
    "ethereum": {
      "usd": 3320.07,
      "usd_24h_change": 0.6269414177062919,
      "usd_7d_change": 7.073824778586594,
      "usd_30d_change": 12.412464924252992,
      "usd_1y_change": 1.561673532983617
    },
    "litecoin": {
      "usd": 75.6,
      "usd_24h_change": 1.3628441163201948,
      "usd_7d_change": -6.8054718736524205,
      "usd_30d_change": -0.6087167478754808,
      "usd_1y_change": -39.972412285303214
    },
    "monero": {
      "usd": 587.65,
      "usd_24h_change": -6.303781780880668,
      "usd_7d_change": 18.179664512080667,
      "usd_30d_change": 33.14875128030464,
      "usd_1y_change": 173.155180320723
    },
    "ripple": {
      "usd": 2.05,
      "usd_24h_change": -0.3272208377075114,
      "usd_7d_change": -1.6920682669301457,
      "usd_30d_change": 10.194653622707134,
      "usd_1y_change": -34.04363820219764
    },
    "shiba-inu": {
      "usd": 8.4e-06,
      "usd_24h_change": -1.110433751312973,
      "usd_7d_change": -3.100994663348465,
      "usd_30d_change": 13.790027345232977,
      "usd_1y_change": -63.007029413980916
    },
    "solana": {
      "usd": 142.32,
      "usd_24h_change": -1.1224558548809878,
      "usd_7d_change": 4.407905735101432,
      "usd_30d_change": 14.181802198682952,
      "usd_1y_change": -40.16282709859834
    },
    "stellar": {
      "usd": 0.226495,
      "usd_24h_change": -0.20404485311961992,
      "usd_7d_change": -0.5669821306449564,
      "usd_30d_change": 4.706039421656514,
      "usd_1y_change": -50.7411105839987
    },
    "the-open-network": {
      "usd": 1.72,
      "usd_24h_change": 0.17937553358296035,
      "usd_7d_change": -1.5237634942800027,
      "usd_30d_change": 19.14914892132429,
      "usd_1y_change": -67.68209971215681
    },
    "tron": {
      "usd": 0.31731,
      "usd_24h_change": 1.4664867052204866,
      "usd_7d_change": 6.26530603969877,
      "usd_30d_change": 13.52367106124002,
      "usd_1y_change": 32.353746495212135
    },
    "zcash": {
      "usd": 397.87,
      "usd_24h_change": -1.73032034433237,
      "usd_7d_change": 4.056064079646415,
      "usd_30d_change": -3.4757974612265374,
      "usd_1y_change": 660.2035827437489
    }
  }
}