{
  "updated_at_utc": "2025-12-21T23:43:48.176972+00:00",
  "vs_currency": "usd",
  "prices": {
    "aave": {
      "usd": 164.81,
      "usd_24h_change": -8.435414190235647,
      "usd_7d_change": -12.606460919372422,
      "usd_30d_change": 6.454567776194748,
      "usd_1y_change": -44.80100431735469
    },
    "binancecoin": {
      "usd": 857.56,
      "usd_24h_change": 0.5816574301420945,
      "usd_7d_change": -2.5855037386167115,
      "usd_30d_change": 2.9087021561982898,
      "usd_1y_change": 30.117098902832563
    },
    "bitcoin": {
      "usd": 88496,
      "usd_24h_change": 0.2648205111440311,
      "usd_7d_change": 0.021214160400930514,
      "usd_30d_change": 3.858187324601797,
      "usd_1y_change": -8.711662087684669
    },
    "bitcoin-cash": {
      "usd": 589.21,
      "usd_24h_change": -0.5826041145917307,
      "usd_7d_change": 5.6657589017101975,
      "usd_30d_change": 9.381756335589934,
      "usd_1y_change": 30.787408473323495
    },
    "cardano": {
      "usd": 0.365497,
      "usd_24h_change": -2.0634272592650866,
      "usd_7d_change": -7.536270120008338,
      "usd_30d_change": -11.536002644049507,
      "usd_1y_change": -59.38646691693458
    },
    "dogecoin": {
      "usd": 0.130889,
      "usd_24h_change": -0.8256883044175689,
      "usd_7d_change": -2.2070577697252625,
      "usd_30d_change": -7.34621704486729,
      "usd_1y_change": -59.023728792163446
    },
    "ethereum": {
      "usd": 3002.55,
      "usd_24h_change": 0.9520209200360843,
      "usd_7d_change": -2.5645013680784827,
      "usd_30d_change": 8.593735217949193,
      "usd_1y_change": -9.680522065709111
    },
    "litecoin": {
      "usd": 76.7,
      "usd_24h_change": -1.510454747388807,
      "usd_7d_change": -2.3849744737841987,
      "usd_30d_change": -7.4233262883518325,
      "usd_1y_change": -23.57178585520932
    },
    "monero": {
      "usd": 471.27,
      "usd_24h_change": -1.1729549437551092,
      "usd_7d_change": 15.472697753159991,
      "usd_30d_change": 40.84322321291473,
      "usd_1y_change": 155.5611673384832
    },
    "ripple": {
      "usd": 1.92,
      "usd_24h_change": -0.4651322412757661,
      "usd_7d_change": -3.182093439530936,
      "usd_30d_change": -1.6794658150769939,
      "usd_1y_change": -13.85792074223664
    },
    "shiba-inu": {
      "usd": 7.27e-06,
      "usd_24h_change": -2.2545745181874346,
      "usd_7d_change": -9.751127269405906,
      "usd_30d_change": -7.973697239653181,
      "usd_1y_change": -66.39738609113573
    },
    "solana": {
      "usd": 125.9,
      "usd_24h_change": 0.19313068839638656,
      "usd_7d_change": -3.080890639536148,
      "usd_30d_change": -2.3831593051661613,
      "usd_1y_change": -30.255269801095192
    },
    "stellar": {
      "usd": 0.216215,
      "usd_24h_change": -0.9387713973419403,
      "usd_7d_change": -5.566810970888571,
      "usd_30d_change": -6.513762531222805,
      "usd_1y_change": -39.265748685629795
    },
    "the-open-network": {
      "usd": 1.46,
      "usd_24h_change": -2.0184086610587157,
      "usd_7d_change": -6.055596163254731,
      "usd_30d_change": -4.7083606060745735,
      "usd_1y_change": -72.39797890684166
    },
    "tron": {
      "usd": 0.288223,
      "usd_24h_change": 2.6361979035218526,
      "usd_7d_change": 3.995281039147072,
      "usd_30d_change": 4.158650721184792,
      "usd_1y_change": 17.966835476213365
    },
    "zcash": {
      "usd": 442.03,
      "usd_24h_change": -1.0601767968501976,
      "usd_7d_change": 11.087451640702604,
      "usd_30d_change": -17.351480955921357,
      "usd_1y_change": 721.1289510024541
    }
  }
}